pymodulo/__init__.py
pymodulo/metrics.py
pymodulo/DataLoader/CSVDataLoader.py
pymodulo/DataLoader/DataLoader.py
pymodulo/DataLoader/__init__.py
pymodulo/SpatialStratification/CustomStratification.py
pymodulo/SpatialStratification/GridStratification.py
pymodulo/SpatialStratification/RoadStratification.py
pymodulo/SpatialStratification/SpatialStratification.py
pymodulo/SpatialStratification/__init__.py
pymodulo/VehicleSelector/GreedyVehicleSelector.py
pymodulo/VehicleSelector/MaxPointsVehicleSelector.py
pymodulo/VehicleSelector/RandomVehicleSelector.py
pymodulo/VehicleSelector/VehicleSelector.py
pymodulo/VehicleSelector/__init__.py
pymodulo-0.1.0.dist-info/LICENSE
pymodulo-0.1.0.dist-info/METADATA
pymodulo-0.1.0.dist-info/WHEEL
pymodulo-0.1.0.dist-info/top_level.txt
pymodulo-0.1.0.dist-info/RECORD
