Metadata-Version: 2.1
Name: pymodulo
Version: 0.1.0
Summary: Vehicle selection for drive-by sensing deployments to maximize coverage
Home-page: https://github.com/microsoft/Modulo
Author: Dhruv Agarwal
Author-email: dhruv.agarwal@alumni.ashoka.edu.in
License: UNKNOWN
Platform: UNKNOWN
Classifier: Programming Language :: Python :: 3
Classifier: License :: OSI Approved :: MIT License
Classifier: Operating System :: OS Independent
Classifier: Intended Audience :: Science/Research
Requires-Python: >=3.6
License-File: LICENSE
Requires-Dist: pandas (>=1.0.3)
Requires-Dist: pymongo (>=3.10.1)
